pyanyapi/__init__.py
pyanyapi/_compat.py
pyanyapi/decorators.py
pyanyapi/exceptions.py
pyanyapi/helpers.py
pyanyapi/interfaces.py
pyanyapi/parsers.py
pyanyapi-0.6.1.dist-info/DESCRIPTION.rst
pyanyapi-0.6.1.dist-info/METADATA
pyanyapi-0.6.1.dist-info/RECORD
pyanyapi-0.6.1.dist-info/WHEEL
pyanyapi-0.6.1.dist-info/metadata.json
pyanyapi-0.6.1.dist-info/top_level.txt
