Metadata-Version: 2.0
Name: pyanyapi
Version: 0.6.1
Summary: Tools for convenient interface creation over various types of data in a declarative way.
Home-page: https://github.com/Stranger6667/pyanyapi
Author: Dmitry Dygalo
Author-email: dadygalo@gmail.com
License: MIT
Keywords: parsing,interface,xml,json,csv,yaml,API,XPath,regexp
Platform: UNKNOWN
Classifier: Development Status :: 5 - Production/Stable
Classifier: Environment :: Console
Classifier: Intended Audience :: Developers
Classifier: Operating System :: OS Independent
Classifier: License :: OSI Approved :: MIT License
Classifier: Programming Language :: Python
Classifier: Programming Language :: Python :: 2.6
Classifier: Programming Language :: Python :: 2.7
Classifier: Programming Language :: Python :: 3.2
Classifier: Programming Language :: Python :: 3.3
Classifier: Programming Language :: Python :: 3.4
Classifier: Programming Language :: Python :: 3.5
Classifier: Programming Language :: Python :: Implementation :: CPython
Classifier: Programming Language :: Python :: Implementation :: PyPy
Classifier: Programming Language :: Python :: Implementation :: Jython
Classifier: Topic :: Text Processing :: General
Classifier: Topic :: Utilities
Requires-Dist: PyYAML (>=3.11)
Requires-Dist: lxml
Requires-Dist: ujson
